Lib/site-packages/pip/__init__.py
Lib/site-packages/pip/__main__.py
Lib/site-packages/pip/__pip-runner__.py
Lib/site-packages/pip/py.typed
Lib/site-packages/pip/_internal/__init__.py
Lib/site-packages/pip/_internal/build_env.py
Lib/site-packages/pip/_internal/cache.py
Lib/site-packages/pip/_internal/configuration.py
Lib/site-packages/pip/_internal/exceptions.py
Lib/site-packages/pip/_internal/main.py
Lib/site-packages/pip/_internal/pyproject.py
Lib/site-packages/pip/_internal/self_outdated_check.py
Lib/site-packages/pip/_internal/wheel_builder.py
Lib/site-packages/pip/_internal/cli/__init__.py
Lib/site-packages/pip/_internal/cli/autocompletion.py
Lib/site-packages/pip/_internal/cli/base_command.py
Lib/site-packages/pip/_internal/cli/cmdoptions.py
Lib/site-packages/pip/_internal/cli/command_context.py
Lib/site-packages/pip/_internal/cli/index_command.py
Lib/site-packages/pip/_internal/cli/main.py
Lib/site-packages/pip/_internal/cli/main_parser.py
Lib/site-packages/pip/_internal/cli/parser.py
Lib/site-packages/pip/_internal/cli/progress_bars.py
Lib/site-packages/pip/_internal/cli/req_command.py
Lib/site-packages/pip/_internal/cli/spinners.py
Lib/site-packages/pip/_internal/cli/status_codes.py
Lib/site-packages/pip/_internal/commands/__init__.py
Lib/site-packages/pip/_internal/commands/cache.py
Lib/site-packages/pip/_internal/commands/check.py
Lib/site-packages/pip/_internal/commands/completion.py
Lib/site-packages/pip/_internal/commands/configuration.py
Lib/site-packages/pip/_internal/commands/debug.py
Lib/site-packages/pip/_internal/commands/download.py
Lib/site-packages/pip/_internal/commands/freeze.py
Lib/site-packages/pip/_internal/commands/hash.py
Lib/site-packages/pip/_internal/commands/help.py
Lib/site-packages/pip/_internal/commands/index.py
Lib/site-packages/pip/_internal/commands/inspect.py
Lib/site-packages/pip/_internal/commands/install.py
Lib/site-packages/pip/_internal/commands/list.py
Lib/site-packages/pip/_internal/commands/search.py
pybrawlstars-1.0.7.dist-info/METADATA
pybrawlstars-1.0.7.dist-info/WHEEL
pybrawlstars-1.0.7.dist-info/top_level.txt
pybrawlstars-1.0.7.dist-info/RECORD
